redis_caching/__init__.py
redis_caching/caching.py
flask_redis_caching-1.0.3.dist-info/METADATA
flask_redis_caching-1.0.3.dist-info/WHEEL
flask_redis_caching-1.0.3.dist-info/top_level.txt
flask_redis_caching-1.0.3.dist-info/RECORD
