Metadata-Version: 2.1
Name: flask-redis-caching
Version: 1.0.3
Summary: Flask Redis Caching is a Python library that provides caching functionalities using Redis for storing and retrieving cached values in Flask applications.
Author: Maksymilian Sawicz
Requires-Dist: flask-redis
